gradio_tunneling/__init__.py
gradio_tunneling/frpc_darwin_amd64_v0.2
gradio_tunneling/frpc_darwin_arm64_v0.2
gradio_tunneling/frpc_linux_amd64_v0.2
gradio_tunneling/frpc_linux_arm64_v0.2
gradio_tunneling/frpc_windows_amd64_v0.2
gradio_tunneling/frpc_windows_amd64_v0.2.exe
gradio_tunneling/main.py
gradio_tunneling-0.8.1.dist-info/METADATA
gradio_tunneling-0.8.1.dist-info/WHEEL
gradio_tunneling-0.8.1.dist-info/entry_points.txt
gradio_tunneling-0.8.1.dist-info/licenses/LICENSE
gradio_tunneling-0.8.1.dist-info/RECORD
