Metadata-Version: 2.4
Name: gradio-tunneling
Version: 0.8.1
Summary: A tool to help you expose your non gradio app using gradio
License: The MIT License (MIT)
License-File: LICENSE
Classifier: License :: OSI Approved :: Apache Software License
Classifier: Operating System :: OS Independent
Classifier: Programming Language :: Python :: 3
Requires-Python: >=3.8
Requires-Dist: requests
